pymsm/__init__.py
pymsm/archive/simulation_trials.ipynb
pymsm/competing_risks_model.py
pymsm/datasets/__init__.py
pymsm/datasets/aidssi.csv
pymsm/datasets/covid_hosp_data.csv
pymsm/datasets/ebmt_long.csv
pymsm/datasets/ebmt_wide.csv
pymsm/datasets/rotterdam.csv
pymsm/event_specific_fitter.py
pymsm/examples/AIDSI_example.ipynb
pymsm/examples/COVID_hospitalization_example.ipynb
pymsm/examples/EBMT_example.ipynb
pymsm/examples/Rotterdam_example.ipynb
pymsm/examples/__init__.py
pymsm/examples/ebmt_states.png
pymsm/examples/first_example.ipynb
pymsm/examples/first_example_utils.py
pymsm/examples/simulation_example.ipynb
pymsm/multi_state_competing_risks_model.py
pymsm/plotting.py
pymsm/simulation.py
pymsm/state_diagram.py
pymsm/statistics.py
pymsm/survival_tree_fitter.py
pymsm/utils.py
pymsm-0.1.7.dist-info/LICENSE
pymsm-0.1.7.dist-info/WHEEL
pymsm-0.1.7.dist-info/METADATA
pymsm-0.1.7.dist-info/RECORD
