Metadata-Version: 2.1
Name: pymsm
Version: 0.1.7
Summary: Multstate modeling in Python
Home-page: https://hrossman.github.io/pymsm/
License: MIT
Keywords: multstate,competing risks,survival
Author: Hagai Rossman, Ayya Keshet, Malka Gorfine
Requires-Python: >=3.8,<4.0
Classifier: License :: OSI Approved :: MIT License
Classifier: Programming Language :: Python :: 3
Classifier: Programming Language :: Python :: 3.10
Classifier: Programming Language :: Python :: 3.8
Classifier: Programming Language :: Python :: 3.9
Requires-Dist: joblib (>=1.1.0,<2.0.0)
Requires-Dist: lifelines (>=0.26.4,<0.27.0)
Requires-Dist: matplotlib (>=3.5.1,<4.0.0)
Requires-Dist: numpy (>=1.22.2,<2.0.0)
Requires-Dist: pandas (>=1.4.1,<2.0.0)
Requires-Dist: scikit-learn (>=1.0.2,<2.0.0)
Requires-Dist: tabulate (>=0.8.9,<0.9.0)
Requires-Dist: tqdm (>=4.62.3,<5.0.0)
Project-URL: Documentation, https://hrossman.github.io/pymsm/
Project-URL: Repository, https://github.com/hrossman/pymsm
